gconnectLyftron.py
main.py
queryConverterRusab-0.0.2.dist-info/METADATA
queryConverterRusab-0.0.2.dist-info/WHEEL
queryConverterRusab-0.0.2.dist-info/top_level.txt
queryConverterRusab-0.0.2.dist-info/RECORD
