Metadata-Version: 2.1
Name: queryConverterRusab
Version: 0.0.2
Summary: Process json and convert it into dataframes
Home-page: https://github.com/#
Author: Rusab Naeem
Author-email: rusabkhan7@gmail.com
License: UNKNOWN
Platform: UNKNOWN
Requires-Dist: google-api-core (~=1.23.0)
Requires-Dist: google-api-python-client (~=1.12.5)
Requires-Dist: google-auth (~=1.23.0)
Requires-Dist: google-auth-httplib2 (~=0.0.4)
Requires-Dist: google-auth-oauthlib (~=0.4.2)
Requires-Dist: googleapis-common-protos (~=1.52.0)
Requires-Dist: gspread (~=3.6.0)
Requires-Dist: oauth2client (~=4.1.3)
Requires-Dist: oauthlib (~=3.1.0)
Requires-Dist: pandas (~=1.1.4)
Requires-Dist: pandasql (~=0.7.3)
Requires-Dist: SQLAlchemy (==1.3.20)
